systembolaget_api/__init__.py
systembolaget_api/bolaget.py
systembolaget_api/constants.py
systembolaget_api/filters.py
systembolaget_api/session.py
systembolaget_api-0.0.3.dist-info/licenses/LICENSE
systembolaget_api-0.0.3.dist-info/METADATA
systembolaget_api-0.0.3.dist-info/WHEEL
systembolaget_api-0.0.3.dist-info/top_level.txt
systembolaget_api-0.0.3.dist-info/RECORD
