Metadata-Version: 2.4
Name: systembolaget_api
Version: 0.0.3
Summary: A python API wrapper for systembolaget.se
Author-email: dunderrrrrr <emil.bjorkroth@gmail.com>
Requires-Python: >=3.10
License-File: LICENSE
Requires-Dist: httpx>=0.28.1
Requires-Dist: pre-commit>=4.5.1
Requires-Dist: pytest>=9.0.2
Requires-Dist: respx>=0.22.0
Requires-Dist: mypy>=1.19.1
Requires-Dist: ruff>=0.14.13
Dynamic: license-file
